geneticanalyzer/GeneticAnalyzer.py
geneticanalyzer/__init__.py
geneticanalyzer-1.1.7.dist-info/LICENSE
geneticanalyzer-1.1.7.dist-info/METADATA
geneticanalyzer-1.1.7.dist-info/WHEEL
geneticanalyzer-1.1.7.dist-info/top_level.txt
geneticanalyzer-1.1.7.dist-info/RECORD
