Metadata-Version: 2.1
Name: geneticanalyzer
Version: 1.1.7
Summary: A library for visualizing genetic algorithm lineages
Author-email: Kovács Bálint-Hunor <kovacsbalinthunor53@gmail.com>
Project-URL: Homepage, https://github.com/MemerGamer/GeneticAnalyzer
Project-URL: Issues, https://github.com/MemerGamer/GeneticAnalyzer/issues
Classifier: Programming Language :: Python :: 3
Classifier: License :: OSI Approved :: GNU General Public License v3 (GPLv3)
Classifier: Operating System :: OS Independent
Requires-Python: >=3.9
License-File: LICENSE
Requires-Dist: matplotlib>=3.10.0
Requires-Dist: networkx>=3.4.2
Requires-Dist: pygraphviz>=1.14
Requires-Dist: scipy>=1.14.1
